dpflow/__init__.py
amp_flow-0.0.0.dist-info/METADATA
amp_flow-0.0.0.dist-info/WHEEL
amp_flow-0.0.0.dist-info/RECORD
